ccxt_backtesting_exchange/__init__.py
ccxt_backtesting_exchange/backtester.py
ccxt_backtesting_exchange/clock.py
ccxt_backtesting_exchange/data_feed.py
ccxt_backtesting_exchange/market_data.py
ccxt_backtesting_exchange/utils.py
ccxt_backtesting_exchange-0.1.0.dist-info/LICENSE
ccxt_backtesting_exchange-0.1.0.dist-info/METADATA
ccxt_backtesting_exchange-0.1.0.dist-info/WHEEL
ccxt_backtesting_exchange-0.1.0.dist-info/RECORD
