Metadata-Version: 2.3
Name: ccxt_backtesting_exchange
Version: 0.1.0
Summary: A backtesting simulator based on ccxt for cryptocurrency trading strategies
License: MIT
Keywords: ccxt,backtesting,cryptocurrency,trading,simulator
Author: Abdulhakeem
Author-email: abdulhakeemmustapha@gmail.com
Requires-Python: >=3.11
Classifier: Development Status :: 3 - Alpha
Classifier: Intended Audience :: Developers
Classifier: License :: OSI Approved :: MIT License
Classifier: Programming Language :: Python :: 3
Classifier: Programming Language :: Python :: 3.11
Classifier: Programming Language :: Python :: 3.12
Classifier: Topic :: Office/Business :: Financial :: Investment
Classifier: Topic :: Software Development :: Libraries :: Python Modules
Requires-Dist: ccxt (>=4.4.51,<5.0.0)
Requires-Dist: numpy (>=2.2.2,<3.0.0)
Requires-Dist: pandas (>=2.2.3,<3.0.0)
Requires-Dist: tqdm (>=4.64.0,<5.0.0)
